{
  "week_code": "2026-W07",
  "week_period": "09.02.2026 - 13.02.2026",
  "menu": {
    "Понедельник": {
      "Салат": [
        "Купеческий",
        "Мимоза"
      ],
      "Суп": [
        "Солянка",
        "Куриный бульон с яйцом"
      ],
      "Горячее": [
        "Курица тереяки",
        "Минтай под овощами"
      ],
      "Гарнир": [
        "Рис отварной",
        "Картофельное пюре"
      ]
    },
    "Вторник": {
      "Салат": [
        "Немецкий",
        "Нептун"
      ],
      "Суп": [
        "Борщ",
        "Гороховый с копченостями"
      ],
      "Горячее": [
        "Бигус с говядиной",
        "Куриная голень с удоном и овощами"
      ],
      "Гарнир": []
    },
    "Среда": {
      "Салат": [
        "Оливье",
        "Салат Крабовый"
      ],
      "Суп": [
        "Бухлер",
        "Рассольник"
      ],
      "Горячее": [
        "Мясо по французски",
        "Щницель куриный в сухарях"
      ],
      "Гарнир": [
        "Соба с овощами",
        "Овощи печеные"
      ]
    },
    "Четверг": {
      "Салат": [
        "Обжорка с курицей",
        "Дальневосточный"
      ],
      "Суп": [
        "Харчо",
        "Куриный с клецками"
      ],
      "Горячее": [
        "Минтай с овощами",
        "Гуляш из говядины с перловой кашей"
      ],
      "Гарнир": []
    },
    "Пятница": {
      "Салат": [
        "Лукошко",
        "Столичный с уткой"
      ],
      "Суп": [
        "Полевой с гречкой и свининой",
        "Лагман"
      ],
      "Горячее": [
        "Курица в сливочном соусе",
        "Поджарка из свинины"
      ],
      "Гарнир": [
        "Картофель жареный с грибами",
        "Гречка отварная"
      ]
    }
  },
  "updated_at": "2026-02-02T05:54:06.338Z",
  "created_at": "2026-01-23T11:13:02.199Z"
}